CHANGES.txt
README.txt
buildout.cfg
setup.py
src/z3c/__init__.py
src/z3c.conditionalviews.egg-info/PKG-INFO
src/z3c.conditionalviews.egg-info/SOURCES.txt
src/z3c.conditionalviews.egg-info/dependency_links.txt
src/z3c.conditionalviews.egg-info/namespace_packages.txt
src/z3c.conditionalviews.egg-info/not-zip-safe
src/z3c.conditionalviews.egg-info/requires.txt
src/z3c.conditionalviews.egg-info/top_level.txt
src/z3c/conditionalviews/README.txt
src/z3c/conditionalviews/__init__.py
src/z3c/conditionalviews/adapters.py
src/z3c/conditionalviews/configure.zcml
src/z3c/conditionalviews/etag.py
src/z3c/conditionalviews/ftesting.zcml
src/z3c/conditionalviews/interfaces.py
src/z3c/conditionalviews/lastmodification.py
src/z3c/conditionalviews/tests.py
src/z3c/conditionalviews/validation.txt