Metadata-Version: 1.0
Name: z3c.conditionalviews
Version: 1.0
Summary: This package intergrates with the zope publisher to validate conditional
